basecash/__init__.py
basecash-0.0.1.dist-info/DESCRIPTION.rst
basecash-0.0.1.dist-info/METADATA
basecash-0.0.1.dist-info/RECORD
basecash-0.0.1.dist-info/WHEEL
basecash-0.0.1.dist-info/metadata.json
basecash-0.0.1.dist-info/top_level.txt
