Metadata-Version: 2.0
Name: basecash
Version: 0.0.1
Summary: Basic home expense and budgetting tool
Home-page: UNKNOWN
Author: Ruud de Jong
Author-email: UNKNOWN
License: BSD
